mlflow_mlserver_docker/Dockerfile
mlflow_mlserver_docker/__init__.py
mlflow_mlserver_docker/cli.py
mlflow_mlserver_docker/main.py
mlflow_mlserver_docker-0.4.1.dist-info/entry_points.txt
mlflow_mlserver_docker-0.4.1.dist-info/WHEEL
mlflow_mlserver_docker-0.4.1.dist-info/METADATA
mlflow_mlserver_docker-0.4.1.dist-info/RECORD
