Metadata-Version: 2.1
Name: mlflow-mlserver-docker
Version: 0.4.1
Summary: Package mlflow models as mlserver docker images
Home-page: https://github.com/dingobar/mlflow-mlserver-docker
Author: Martin Morset
Author-email: mmorset@gmail.com
Requires-Python: >=3.8,<4.0
Classifier: Programming Language :: Python :: 3
Classifier: Programming Language :: Python :: 3.8
Classifier: Programming Language :: Python :: 3.9
Classifier: Programming Language :: Python :: 3.10
Requires-Dist: boto3 (>=1.24.76,<2.0.0)
Requires-Dist: mlflow-skinny (>=1.28.0,<2.0.0)
Requires-Dist: python-dotenv (>=0.21.0,<0.22.0)
Requires-Dist: python-on-whales (>=0.52.0,<0.53.0)
Requires-Dist: typer[all] (>=0.6.1,<0.7.0)
